{
  "stats": {
    "minecraft:used": {
      "avoidminer:mining_upgrade_tier_1": 1,
      "minecraft:netherite_sword": 45,
      "avoidminer:raw_magnetite_block": 29,
      "avoidminer:avoid_miner_tier_3": 2,
      "avoidminer:speed_upgrade_tier_3": 13,
      "minecraft:iron_pickaxe": 13,
      "avoidminer:avoid_miner_tier_1": 1,
      "minecraft:jungle_log": 2,
      "minecraft:netherite_axe": 29,
      "avoidminer:avoid_lootr": 1,
      "minecraft:creeper_spawn_egg": 22,
      "minecraft:spruce_log": 6,
      "minecraft:stone": 5,
      "minecraft:villager_spawn_egg": 10,
      "avoidminer:battery": 4,
      "minecraft:netherite_pickaxe": 1,
      "avoidminer:energy_upgrade_tier_1": 8,
      "avoidminer:energy_link": 7,
      "avoidminer:avoid_processor_tier_3": 2,
      "avoidminer:avoid_processor_tier_1": 1,
      "avoidminer:magnetite_ore": 20
    },
    "minecraft:picked_up": {
      "avoidminer:mining_upgrade_tier_3": 1,
      "avoidminer:mining_upgrade_tier_2": 1,
      "minecraft:cobblestone": 1,
      "avoidminer:mining_upgrade_tier_1": 4,
      "avoidminer:fortune_upgrade": 2,
      "avoidminer:mining_core": 1,
      "avoidminer:upgrade_tier_3": 2,
      "avoidminer:avoid_processor_tier_3": 1,
      "avoidminer:avoid_miner_tier_3": 1,
      "avoidminer:nether_upgrade": 4,
      "avoidminer:upgrade_tier_2": 1,
      "avoidminer:raw_magnetite_block": 1,
      "avoidminer:raw_magnetite": 10,
      "minecraft:coal_block": 84,
      "avoidminer:magnetite_ingot": 3,
      "avoidminer:magnetite_powder": 10,
      "avoidminer:creeper_card": 1,
      "avoidminer:energy_upgrade_tier_3": 1,
      "avoidminer:energy_upgrade_tier_1": 2,
      "avoidminer:skeleton_card": 1,
      "avoidminer:silk_upgrade": 1,
      "avoidminer:speed_upgrade_tier_1": 1,
      "avoidminer:speed_upgrade_tier_2": 2,
      "avoidminer:magnetite_nugget": 2,
      "minecraft:gunpowder": 22,
      "avoidminer:speed_upgrade_tier_3": 8,
      "avoidminer:botany_upgrade": 1,
      "avoidminer:processing_core": 1
    },
    "minecraft:dropped": {
      "avoidminer:mining_core": 1,
      "avoidminer:magnetite_ingot": 3,
      "avoidminer:magnetite_nugget": 2,
      "avoidminer:creeper_card": 1,
      "avoidminer:speed_upgrade_tier_3": 7,
      "avoidminer:speed_upgrade_tier_2": 1,
      "avoidminer:speed_upgrade_tier_1": 1,
      "avoidminer:skeleton_card": 1,
      "avoidminer:upgrade_tier_3": 2,
      "avoidminer:upgrade_tier_2": 1,
      "avoidminer:nether_upgrade": 2,
      "avoidminer:botany_upgrade": 1,
      "avoidminer:mining_upgrade_tier_1": 3,
      "avoidminer:processing_core": 1,
      "avoidminer:mining_upgrade_tier_2": 1,
      "avoidminer:fortune_upgrade": 2
    },
    "minecraft:custom": {
      "minecraft:time_since_rest": 652986,
      "minecraft:walk_one_cm": 37968,
      "minecraft:leave_game": 32,
      "minecraft:mob_kills": 30,
      "minecraft:play_time": 326493,
      "minecraft:damage_dealt": 5978,
      "minecraft:jump": 93,
      "minecraft:time_since_death": 326493,
      "minecraft:drop": 30,
      "minecraft:sprint_one_cm": 6965,
      "minecraft:total_world_time": 333698,
      "minecraft:fly_one_cm": 623,
      "minecraft:crouch_one_cm": 1183,
      "minecraft:sneak_time": 627
    },
    "minecraft:killed": {
      "minecraft:creeper": 20,
      "minecraft:villager": 10
    },
    "minecraft:mined": {
      "avoidminer:avoid_miner_tier_3": 1,
      "avoidminer:magnetite_ore": 10,
      "avoidminer:raw_magnetite_block": 1,
      "avoidminer:avoid_processor_tier_3": 1,
      "minecraft:stone": 1
    }
  },
  "DataVersion": 4790
}